{
  "group": "ЭМ143д",
  "monday": "24.11.2025",
  "saturday": "29.11.2025",
  "schedule": {
    "22.11.2025": {
      "day": "Сб-2",
      "pairs": {
        "1": [
          "Инф. техн. в проф. деят. | Салимьянова З.Р."
        ],
        "2": [
          "Инф. техн. в проф. деят. | Салимьянова З.Р."
        ],
        "3": [
          "Инф. техн. в проф. деят. | Салимьянова З.Р."
        ],
        "4": [
          "Инф. техн. в проф. деят. | Салимьянова З.Р."
        ]
      },
      "pairs_cols": {
        "1": [
          "Инф. техн. в проф. деят. | Салимьянова З.Р.",
          ""
        ],
        "2": [
          "Инф. техн. в проф. деят. | Салимьянова З.Р.",
          ""
        ],
        "3": [
          "",
          "Инф. техн. в проф. деят. | Салимьянова З.Р."
        ],
        "4": [
          "",
          "Инф. техн. в проф. деят. | Салимьянова З.Р."
        ]
      },
      "merge": {},
      "lessons": [
        "1 пара: ① Инф. техн. в проф. деят. | Салимьянова З.Р.",
        "2 пара: ① Инф. техн. в проф. деят. | Салимьянова З.Р.",
        "3 пара: ② Инф. техн. в проф. деят. | Салимьянова З.Р.",
        "4 пара: ② Инф. техн. в проф. деят. | Салимьянова З.Р.",
        "5 пара: НЕТ",
        "6 пара: НЕТ",
        "7 пара: НЕТ",
        "8 пара: НЕТ"
      ]
    },
    "23.11.2025": {
      "day": "Вс-2",
      "pairs": {},
      "pairs_cols": {},
      "merge": {},
      "lessons": [
        "1 пара: НЕТ",
        "2 пара: НЕТ",
        "3 пара: НЕТ",
        "4 пара: НЕТ",
        "5 пара: НЕТ",
        "6 пара: НЕТ",
        "7 пара: НЕТ",
        "8 пара: НЕТ"
      ]
    },
    "24.11.2025": {
      "day": "Пн-1",
      "pairs": {
        "1": [
          "Инженер. графика (Лек.) | 18 | Набиуллина И.Ф.",
          "Инженер. графика (Лек.) | 17 | Мрясова О.Л."
        ],
        "2": [
          "Материаловедение (Лек.) | 5м | Данилова Н.В."
        ],
        "3": [
          "Электротехника и электроника (Лек.) | 12 | Муллазанова Л.А."
        ],
        "4": [
          "Физическая культура (Лек.) | СП1.2 | Белоусова Л.А."
        ]
      },
      "pairs_cols": {
        "1": [
          "Инженер. графика (Лек.) | 18 | Набиуллина И.Ф.",
          "Инженер. графика (Лек.) | 17 | Мрясова О.Л."
        ]
      },
      "merge": {
        "2": "Материаловедение (Лек.) | 5м | Данилова Н.В.",
        "3": "Электротехника и электроника (Лек.) | 12 | Муллазанова Л.А.",
        "4": "Физическая культура (Лек.) | СП1.2 | Белоусова Л.А."
      },
      "lessons": [
        "1 пара:",
        "① Инженер. графика (Лек.) | 18 | Набиуллина И.Ф.",
        "② Инженер. графика (Лек.) | 17 | Мрясова О.Л.",
        "2 пара: Материаловедение (Лек.) | 5м | Данилова Н.В.",
        "3 пара: Электротехника и электроника (Лек.) | 12 | Муллазанова Л.А.",
        "4 пара: Физическая культура (Лек.) | СП1.2 | Белоусова Л.А.",
        "5 пара: НЕТ",
        "6 пара: НЕТ",
        "7 пара: НЕТ",
        "8 пара: НЕТ"
      ]
    },
    "25.11.2025": {
      "day": "Вт-1",
      "pairs": {
        "1": [
          "Материаловедение (Лек.) | 5м | Данилова Н.В."
        ],
        "2": [
          "Электрические машины и электропривод | 19м | Гарифуллин М.Р."
        ],
        "3": [
          "Электротехника и электроника (Лек.) | 12 | Муллазанова Л.А."
        ]
      },
      "pairs_cols": {
        "2": [
          "",
          "Электрические машины и электропривод | 19м | Гарифуллин М.Р."
        ]
      },
      "merge": {
        "1": "Материаловедение (Лек.) | 5м | Данилова Н.В.",
        "3": "Электротехника и электроника (Лек.) | 12 | Муллазанова Л.А."
      },
      "lessons": [
        "1 пара: Материаловедение (Лек.) | 5м | Данилова Н.В.",
        "2 пара: ② Электрические машины и электропривод | 19м | Гарифуллин М.Р.",
        "3 пара: Электротехника и электроника (Лек.) | 12 | Муллазанова Л.А.",
        "4 пара: НЕТ",
        "5 пара: НЕТ",
        "6 пара: НЕТ",
        "7 пара: НЕТ",
        "8 пара: НЕТ"
      ]
    },
    "26.11.2025": {
      "day": "Ср-1",
      "pairs": {
        "1": [
          "Инф. техн. в проф. деят. | 206 | Салимьянова З.Р."
        ],
        "2": [
          "Инф. техн. в проф. деят. | 206 | Салимьянова З.Р."
        ],
        "3": [
          "История России (Лек.) | 306 | Ширшакова М.В."
        ],
        "4": [
          "Инф. техн. в проф. деят. | 206 | Салимьянова З.Р."
        ],
        "5": [
          "Инф. техн. в проф. деят. | 206 | Салимьянова З.Р."
        ],
        "7": [
          "Иностр. язык в проф.деят. (Лек.) | ДО | Зиязова Г.И."
        ]
      },
      "pairs_cols": {
        "1": [
          "",
          "Инф. техн. в проф. деят. | 206 | Салимьянова З.Р."
        ],
        "2": [
          "",
          "Инф. техн. в проф. деят. | 206 | Салимьянова З.Р."
        ],
        "4": [
          "Инф. техн. в проф. деят. | 206 | Салимьянова З.Р.",
          ""
        ],
        "5": [
          "Инф. техн. в проф. деят. | 206 | Салимьянова З.Р.",
          ""
        ]
      },
      "merge": {
        "3": "История России (Лек.) | 306 | Ширшакова М.В.",
        "7": "Иностр. язык в проф.деят. (Лек.) | ДО | Зиязова Г.И."
      },
      "lessons": [
        "1 пара: ② Инф. техн. в проф. деят. | 206 | Салимьянова З.Р.",
        "2 пара: ② Инф. техн. в проф. деят. | 206 | Салимьянова З.Р.",
        "3 пара: История России (Лек.) | 306 | Ширшакова М.В.",
        "4 пара: ① Инф. техн. в проф. деят. | 206 | Салимьянова З.Р.",
        "5 пара: ① Инф. техн. в проф. деят. | 206 | Салимьянова З.Р.",
        "6 пара: НЕТ",
        "7 пара: Иностр. язык в проф.деят. (Лек.) | ДО | Зиязова Г.И.",
        "8 пара: НЕТ"
      ]
    },
    "27.11.2025": {
      "day": "Чт-1",
      "pairs": {
        "3": [
          "Электротехника и электроника (Лек.) | 12 | Муллазанова Л.А."
        ],
        "4": [
          "Электрические машины и электропривод | 19м | Гарифуллин М.Р."
        ]
      },
      "pairs_cols": {
        "4": [
          "",
          "Электрические машины и электропривод | 19м | Гарифуллин М.Р."
        ]
      },
      "merge": {
        "3": "Электротехника и электроника (Лек.) | 12 | Муллазанова Л.А."
      },
      "lessons": [
        "1 пара: НЕТ",
        "2 пара: НЕТ",
        "3 пара: Электротехника и электроника (Лек.) | 12 | Муллазанова Л.А.",
        "4 пара: ② Электрические машины и электропривод | 19м | Гарифуллин М.Р.",
        "5 пара: НЕТ",
        "6 пара: НЕТ",
        "7 пара: НЕТ",
        "8 пара: НЕТ"
      ]
    },
    "28.11.2025": {
      "day": "Пт-1",
      "pairs": {
        "1": [
          "Инф. техн. в проф. деят. | 34 | Салимьянова З.Р."
        ],
        "2": [
          "Инф. техн. в проф. деят. | 13м | Салимьянова З.Р."
        ],
        "3": [
          "Материаловедение (Лек.) | 5м | Данилова Н.В."
        ],
        "4": [
          "Электрические машины и электропривод | 19м | Гарифуллин М.Р."
        ],
        "5": [
          "Инф. техн. в проф. деят. | 35 | Салимьянова З.Р."
        ],
        "6": [
          "Инф. техн. в проф. деят. | 35 | Салимьянова З.Р."
        ]
      },
      "pairs_cols": {
        "1": [
          "Инф. техн. в проф. деят. | 34 | Салимьянова З.Р.",
          ""
        ],
        "2": [
          "Инф. техн. в проф. деят. | 13м | Салимьянова З.Р.",
          ""
        ],
        "4": [
          "Электрические машины и электропривод | 19м | Гарифуллин М.Р.",
          ""
        ],
        "5": [
          "",
          "Инф. техн. в проф. деят. | 35 | Салимьянова З.Р."
        ],
        "6": [
          "",
          "Инф. техн. в проф. деят. | 35 | Салимьянова З.Р."
        ]
      },
      "merge": {
        "3": "Материаловедение (Лек.) | 5м | Данилова Н.В."
      },
      "lessons": [
        "1 пара: ① Инф. техн. в проф. деят. | 34 | Салимьянова З.Р.",
        "2 пара: ① Инф. техн. в проф. деят. | 13м | Салимьянова З.Р.",
        "3 пара: Материаловедение (Лек.) | 5м | Данилова Н.В.",
        "4 пара: ① Электрические машины и электропривод | 19м | Гарифуллин М.Р.",
        "5 пара: ② Инф. техн. в проф. деят. | 35 | Салимьянова З.Р.",
        "6 пара: ② Инф. техн. в проф. деят. | 35 | Салимьянова З.Р.",
        "7 пара: НЕТ",
        "8 пара: НЕТ"
      ]
    },
    "29.11.2025": {
      "day": "Сб-1",
      "pairs": {},
      "pairs_cols": {},
      "merge": {},
      "lessons": [
        "1 пара: НЕТ",
        "2 пара: НЕТ",
        "3 пара: НЕТ",
        "4 пара: НЕТ",
        "5 пара: НЕТ",
        "6 пара: НЕТ",
        "7 пара: НЕТ",
        "8 пара: НЕТ"
      ]
    },
    "30.11.2025": {
      "day": "Вс-1",
      "pairs": {},
      "pairs_cols": {},
      "merge": {},
      "lessons": [
        "1 пара: НЕТ",
        "2 пара: НЕТ",
        "3 пара: НЕТ",
        "4 пара: НЕТ",
        "5 пара: НЕТ",
        "6 пара: НЕТ",
        "7 пара: НЕТ",
        "8 пара: НЕТ"
      ]
    },
    "01.12.2025": {
      "day": "Пн-2",
      "pairs": {
        "1": [
          "Инженер. графика (Лек.) | 18 | Набиуллина И.Ф.",
          "Инженер. графика (Лек.) | 17 | Мрясова О.Л."
        ],
        "2": [
          "Материаловедение (Лек.) | 6м | Данилова Н.В."
        ],
        "3": [
          "Электротехника и электроника (Лек.) | 12 | Муллазанова Л.А."
        ],
        "4": [
          "Физическая культура (Лек.) | СП1.2 | Белоусова Л.А."
        ]
      },
      "pairs_cols": {
        "1": [
          "Инженер. графика (Лек.) | 18 | Набиуллина И.Ф.",
          "Инженер. графика (Лек.) | 17 | Мрясова О.Л."
        ]
      },
      "merge": {
        "2": "Материаловедение (Лек.) | 6м | Данилова Н.В.",
        "3": "Электротехника и электроника (Лек.) | 12 | Муллазанова Л.А.",
        "4": "Физическая культура (Лек.) | СП1.2 | Белоусова Л.А."
      },
      "lessons": [
        "1 пара:",
        "① Инженер. графика (Лек.) | 18 | Набиуллина И.Ф.",
        "② Инженер. графика (Лек.) | 17 | Мрясова О.Л.",
        "2 пара: Материаловедение (Лек.) | 6м | Данилова Н.В.",
        "3 пара: Электротехника и электроника (Лек.) | 12 | Муллазанова Л.А.",
        "4 пара: Физическая культура (Лек.) | СП1.2 | Белоусова Л.А.",
        "5 пара: НЕТ",
        "6 пара: НЕТ",
        "7 пара: НЕТ",
        "8 пара: НЕТ"
      ]
    },
    "02.12.2025": {
      "day": "Вт-2",
      "pairs": {
        "1": [
          "Инженер. графика (Лек.) | 18 | Набиуллина И.Ф.",
          "Инженер. графика (Лек.) | 17 | Мрясова О.Л."
        ],
        "2": [
          "Электрические машины и электропривод | 19м | Гарифуллин М.Р."
        ]
      },
      "pairs_cols": {
        "1": [
          "Инженер. графика (Лек.) | 18 | Набиуллина И.Ф.",
          "Инженер. графика (Лек.) | 17 | Мрясова О.Л."
        ],
        "2": [
          "",
          "Электрические машины и электропривод | 19м | Гарифуллин М.Р."
        ]
      },
      "merge": {},
      "lessons": [
        "1 пара:",
        "① Инженер. графика (Лек.) | 18 | Набиуллина И.Ф.",
        "② Инженер. графика (Лек.) | 17 | Мрясова О.Л.",
        "2 пара: ② Электрические машины и электропривод | 19м | Гарифуллин М.Р.",
        "3 пара: НЕТ",
        "4 пара: НЕТ",
        "5 пара: НЕТ",
        "6 пара: НЕТ",
        "7 пара: НЕТ",
        "8 пара: НЕТ"
      ]
    },
    "03.12.2025": {
      "day": "Ср-2",
      "pairs": {
        "1": [
          "Прикладная математика (Лек.) | 201 | Салимьянова З.Р."
        ],
        "2": [
          "История России (Лек.) | 306 | Ширшакова М.В."
        ],
        "3": [
          "История России (Лек.) | 306 | Ширшакова М.В."
        ],
        "4": [
          "Инф. техн. в проф. деят. (Лек.) | 206 | Салимьянова З.Р."
        ]
      },
      "pairs_cols": {},
      "merge": {
        "1": "Прикладная математика (Лек.) | 201 | Салимьянова З.Р.",
        "2": "История России (Лек.) | 306 | Ширшакова М.В.",
        "3": "История России (Лек.) | 306 | Ширшакова М.В.",
        "4": "Инф. техн. в проф. деят. (Лек.) | 206 | Салимьянова З.Р."
      },
      "lessons": [
        "1 пара: Прикладная математика (Лек.) | 201 | Салимьянова З.Р.",
        "2 пара: История России (Лек.) | 306 | Ширшакова М.В.",
        "3 пара: История России (Лек.) | 306 | Ширшакова М.В.",
        "4 пара: Инф. техн. в проф. деят. (Лек.) | 206 | Салимьянова З.Р.",
        "5 пара: НЕТ",
        "6 пара: НЕТ",
        "7 пара: НЕТ",
        "8 пара: НЕТ"
      ]
    },
    "04.12.2025": {
      "day": "Чт-2",
      "pairs": {
        "1": [
          "Электрические машины и электропривод (Лек.) | 19м | Гарифуллин М.Р."
        ],
        "3": [
          "Электротехника и электроника (Лек.) | 12 | Муллазанова Л.А."
        ],
        "4": [
          "Охрана труда (Лек.) | 5м | Данилова Н.В."
        ],
        "5": [
          "Инженер. графика (Лек.) | 18 | Набиуллина И.Ф.",
          "Инженер. графика (Лек.) | 17 | Мрясова О.Л."
        ],
        "6": [
          "Иностр. язык в проф.деят. (Лек.) | ДО | Зиязова Г.И."
        ]
      },
      "pairs_cols": {
        "5": [
          "Инженер. графика (Лек.) | 18 | Набиуллина И.Ф.",
          "Инженер. графика (Лек.) | 17 | Мрясова О.Л."
        ]
      },
      "merge": {
        "1": "Электрические машины и электропривод (Лек.) | 19м | Гарифуллин М.Р.",
        "3": "Электротехника и электроника (Лек.) | 12 | Муллазанова Л.А.",
        "4": "Охрана труда (Лек.) | 5м | Данилова Н.В.",
        "6": "Иностр. язык в проф.деят. (Лек.) | ДО | Зиязова Г.И."
      },
      "lessons": [
        "1 пара: Электрические машины и электропривод (Лек.) | 19м | Гарифуллин М.Р.",
        "2 пара: НЕТ",
        "3 пара: Электротехника и электроника (Лек.) | 12 | Муллазанова Л.А.",
        "4 пара: Охрана труда (Лек.) | 5м | Данилова Н.В.",
        "5 пара:",
        "① Инженер. графика (Лек.) | 18 | Набиуллина И.Ф.",
        "② Инженер. графика (Лек.) | 17 | Мрясова О.Л.",
        "6 пара: Иностр. язык в проф.деят. (Лек.) | ДО | Зиязова Г.И.",
        "7 пара: НЕТ",
        "8 пара: НЕТ"
      ]
    },
    "05.12.2025": {
      "day": "Пт-2",
      "pairs": {
        "2": [
          "Электротехника и электроника (Лек.) | 12 | Муллазанова Л.А."
        ],
        "3": [
          "Материаловедение (Лек.) | 24 | Данилова Н.В."
        ]
      },
      "pairs_cols": {},
      "merge": {
        "2": "Электротехника и электроника (Лек.) | 12 | Муллазанова Л.А.",
        "3": "Материаловедение (Лек.) | 24 | Данилова Н.В."
      },
      "lessons": [
        "1 пара: НЕТ",
        "2 пара: Электротехника и электроника (Лек.) | 12 | Муллазанова Л.А.",
        "3 пара: Материаловедение (Лек.) | 24 | Данилова Н.В.",
        "4 пара: НЕТ",
        "5 пара: НЕТ",
        "6 пара: НЕТ",
        "7 пара: НЕТ",
        "8 пара: НЕТ"
      ]
    }
  }
}